Lab/__init__.py
ProAiLab/__init__.py
ProAiLaba/__init__.py
ProAiLaba-0.0.2.dist-info/LICENCE.txt
ProAiLaba-0.0.2.dist-info/METADATA
ProAiLaba-0.0.2.dist-info/WHEEL
ProAiLaba-0.0.2.dist-info/top_level.txt
ProAiLaba-0.0.2.dist-info/RECORD
