Metadata-Version: 2.1
Name: ProAiLaba
Version: 0.0.2
Summary: Lab_Programs
Author: Developer 
Author-email: veeruvk2001@gmail.com
Keywords: Lab,Programs,7th sem
Classifier: Development Status :: 1 - Planning
Classifier: Intended Audience :: Developers
Classifier: Programming Language :: Python :: 3
Classifier: Operating System :: Unix
Classifier: Operating System :: MacOS :: MacOS X
Classifier: Operating System :: Microsoft :: Windows
License-File: LICENCE.txt
